README.md
setup.cfg
setup.py
PANDORA/__init__.py
PANDORA/__version__.py
PANDORA/Contacts/Contacts.py
PANDORA/Contacts/__init__.py
PANDORA/Database/Database.py
PANDORA/Database/Database_functions.py
PANDORA/Database/__init__.py
PANDORA/PMHC/Anchors.py
PANDORA/PMHC/Model.py
PANDORA/PMHC/PMHC.py
PANDORA/PMHC/__init__.py
PANDORA/Pandora/Align.py
PANDORA/Pandora/Modelling_functions.py
PANDORA/Pandora/MyLoop_template.py
PANDORA/Pandora/MyLoop_template_II.py
PANDORA/Pandora/Pandora.py
PANDORA/Pandora/__init__.py
PANDORA/Pandora/cmd_modeller_ini.py
PANDORA/Pandora/cmd_modeller_template.py
PANDORA/Pandora/get_netmhcpan_wrong_pedictions.py
PANDORA/Wrapper/Wrapper.py
PANDORA/Wrapper/__init__.py
PANDORA/Wrapper/run_model.py
csb_pandora.egg-info/PKG-INFO
csb_pandora.egg-info/SOURCES.txt
csb_pandora.egg-info/dependency_links.txt
csb_pandora.egg-info/requires.txt
csb_pandora.egg-info/top_level.txt
test/__init__.py
test/install_git_test.py
test/test_pandora.py