Metadata-Version: 2.1
Name: csb-pandora
Version: 0.9
Summary: Model peptide-MHC I complexes using anchor distance restrains in MODELLER
Home-page: https://github.com/X-lab-3D/PANDORA/tree/master
Author: Dario F. Marzella, Farzaneh M. Parizi, Derek van Tilborg, Li Xue
License: Apache Software License 2.0
Project-URL: Source Code, https://github.com/X-lab-3D/PANDORA/tree/master
Project-URL: Issue tracker, https://github.com/X-lab-3D/PANDORA/issues
Keywords: PANDORA
Platform: UNKNOWN
Classifier: Development Status :: 3 - Alpha
Classifier: Intended Audience :: Science/Research
Classifier: License :: OSI Approved :: Apache Software License
Classifier: Natural Language :: English
Classifier: Programming Language :: Python :: 3.7
Classifier: Programming Language :: Python :: 3.8
Provides-Extra: doc
Provides-Extra: test
